ouro/__init__.py
ouro/__main__.py
ouro/checker.py
ouro/imports_graph.py
ouro/nodes_initializer.py
ouro/reader.py
ouro/utils.py
ouro-0.2.0.dist-info/AUTHORS.md
ouro-0.2.0.dist-info/LICENSE
ouro-0.2.0.dist-info/METADATA
ouro-0.2.0.dist-info/WHEEL
ouro-0.2.0.dist-info/entry_points.txt
ouro-0.2.0.dist-info/top_level.txt
ouro-0.2.0.dist-info/RECORD
