Metadata-Version: 2.1
Name: ouro
Version: 0.2.0
Summary: ouro is a Python package that checks your code for circular (cyclic) imports.
Home-page: https://github.com/abdelrahman0w/ouro
Author: Abdelrahman Abdelkhalek
Author-email: abdelrahman.abdelkhalek@thndr.app
License: MIT license
Keywords: python,ouro,circular,dependency,cycle,cyclic,import,imports
Classifier: Development Status :: 4 - Beta
Classifier: Intended Audience :: Developers
Classifier: License :: OSI Approved :: MIT License
Classifier: Natural Language :: English
Classifier: Programming Language :: Python :: 3
Classifier: Programming Language :: Python :: 3.8
Requires-Python: >=3.8
License-File: LICENSE
License-File: AUTHORS.md
Requires-Dist: pathspec >=0.12.1
